{
  "project_info": {
    "project_number": "530155243967",
    "project_id": "whatsapp-clone-19dcc",
    "storage_bucket": "whatsapp-clone-19dcc.appspot.com"
  },
  "client": [
    {
      "client_info": {
        "mobilesdk_app_id": "1:530155243967:android:8d9a3491ddaa417370f90a",
        "android_client_info": {
          "package_name": "com.smstomail.background"
        }
      },
      "oauth_client": [
        {
          "client_id": "530155243967-jld3l4mgrqun2lnqjsfl9unkkd69scoc.apps.googleusercontent.com",
          "client_type": 3
        }
      ],
      "api_key": [
        {
          "current_key": "AIzaSyBkNH_QBNR_g-ZmLplt9RyG3DzSt_z2k8I"
        }
      ],
      "services": {
        "appinvite_service": {
          "other_platform_oauth_client": [
            {
              "client_id": "530155243967-jld3l4mgrqun2lnqjsfl9unkkd69scoc.apps.googleusercontent.com",
              "client_type": 3
            },
            {
              "client_id": "530155243967-2nngl8fqgmskhooknbqtnts268iha1v8.apps.googleusercontent.com",
              "client_type": 2,
              "ios_info": {
                "bundle_id": "com.example.whatsappClone"
              }
            }
          ]
        }
      }
    },
    {
      "client_info": {
        "mobilesdk_app_id": "1:530155243967:android:3ddae78d73e7292f70f90a",
        "android_client_info": {
          "package_name": "com.whatsapp.clone"
        }
      },
      "oauth_client": [
        {
          "client_id": "530155243967-64hoca1a3hfhfog791lntht1kuht7rh3.apps.googleusercontent.com",
          "client_type": 1,
          "android_info": {
            "package_name": "com.whatsapp.clone",
            "certificate_hash": "7e5b4a342ec698af1501f295d586aca8dcb233bf"
          }
        },
        {
          "client_id": "530155243967-jld3l4mgrqun2lnqjsfl9unkkd69scoc.apps.googleusercontent.com",
          "client_type": 3
        }
      ],
      "api_key": [
        {
          "current_key": "AIzaSyBkNH_QBNR_g-ZmLplt9RyG3DzSt_z2k8I"
        }
      ],
      "services": {
        "appinvite_service": {
          "other_platform_oauth_client": [
            {
              "client_id": "530155243967-jld3l4mgrqun2lnqjsfl9unkkd69scoc.apps.googleusercontent.com",
              "client_type": 3
            },
            {
              "client_id": "530155243967-2nngl8fqgmskhooknbqtnts268iha1v8.apps.googleusercontent.com",
              "client_type": 2,
              "ios_info": {
                "bundle_id": "com.example.whatsappClone"
              }
            }
          ]
        }
      }
    }
  ],
  "configuration_version": "1"
}